{
	"cols": [
	{"id":"","label":"Tempo","pattern":"","type":"number"},
	{"id":"","label":"Total","pattern":"","type":"number"},
	{"id":"","label":"Primeiro","pattern":"","type":"number"},
	{"id":"","label":"Novo","pattern":"","type":"number"}
	],
	"rows": [
	{"c":[{"v":1974,"f":null},{"v":67.5,"f":null},{"v":33.5,"f":null},{"v":34,"f":null}]},
	{"c":[{"v":1975,"f":null},{"v":179,"f":null},{"v":70,"f":null},{"v":109,"f":null}]},
	{"c":[{"v":1976,"f":null},{"v":261.5,"f":null},{"v":109,"f":null},{"v":152.5,"f":null}]},
	{"c":[{"v":1977,"f":null},{"v":309,"f":null},{"v":154,"f":null},{"v":155,"f":null}]},
	{"c":[{"v":1978,"f":null},{"v":334,"f":null},{"v":188.5,"f":null},{"v":145.5,"f":null}]},
	{"c":[{"v":1979,"f":null},{"v":344,"f":null},{"v":195,"f":null},{"v":149,"f":null}]},
	{"c":[{"v":1980,"f":null},{"v":331.5,"f":null},{"v":174.5,"f":null},{"v":157,"f":null}]},
	{"c":[{"v":1981,"f":null},{"v":356.5,"f":null},{"v":182.5,"f":null},{"v":174,"f":null}]},
	{"c":[{"v":1982,"f":null},{"v":316,"f":null},{"v":146.5,"f":null},{"v":169.5,"f":null}]},
	{"c":[{"v":1983,"f":null},{"v":365.8,"f":null},{"v":139.3,"f":null},{"v":226.5,"f":null}]},
	{"c":[{"v":1984,"f":null},{"v":393.9,"f":null},{"v":138.7,"f":null},{"v":255.2,"f":null}]},
	{"c":[{"v":1985,"f":null},{"v":405.4,"f":null},{"v":138.8,"f":null},{"v":266.6,"f":null}]},
	{"c":[{"v":1986,"f":null},{"v":393.6,"f":null},{"v":132.1,"f":null},{"v":261.5,"f":null}]},
	{"c":[{"v":1987,"f":null},{"v":329.2,"f":null},{"v":108.7,"f":null},{"v":220.5,"f":null}]},
	{"c":[{"v":1988,"f":null},{"v":272.9,"f":null},{"v":81.2,"f":null},{"v":191.7,"f":null}]},
	{"c":[{"v":1989,"f":null},{"v":243.5,"f":null},{"v":69.2,"f":null},{"v":174.3,"f":null}]},
	{"c":[{"v":1990,"f":null},{"v":231.1,"f":null},{"v":60.5,"f":null},{"v":170.6,"f":null}]},
	{"c":[{"v":1991,"f":null},{"v":207.5,"f":null},{"v":43.8,"f":null},{"v":163.7,"f":null}]},
	{"c":[{"v":1992,"f":null},{"v":194.1,"f":null},{"v":42.4,"f":null},{"v":151.7,"f":null}]},
	{"c":[{"v":1993,"f":null},{"v":257.5,"f":null},{"v":41.8,"f":null},{"v":215.7,"f":null}]},
	{"c":[{"v":1994,"f":null},{"v":323.8,"f":null},{"v":55.4,"f":null},{"v":268.4,"f":null}]},
	{"c":[{"v":1995,"f":null},{"v":338.4,"f":null},{"v":63.6,"f":null},{"v":274.8,"f":null}]},
	{"c":[{"v":1996,"f":null},{"v":344,"f":null},{"v":71.6,"f":null},{"v":272.4,"f":null}]},
	{"c":[{"v":1997,"f":null},{"v":324.1,"f":null},{"v":64.7,"f":null},{"v":259.4,"f":null}]},
	{"c":[{"v":1998,"f":null},{"v":251.9,"f":null},{"v":44.9,"f":null},{"v":207.0,"f":null}]},
	{"c":[{"v":1999,"f":null},{"v":225.8,"f":null},{"v":33.6,"f":null},{"v":192.2,"f":null}]},
	{"c":[{"v":2000,"f":null},{"v":205.5,"f":null},{"v":27.3,"f":null},{"v":178.2,"f":null}]},
	{"c":[{"v":2001,"f":null},{"v":213.6,"f":null},{"v":34.6,"f":null},{"v":179,"f":null}]},
	{"c":[{"v":2002,"f":null},{"v":270.5,"f":null},{"v":41.1,"f":null},{"v":229.4,"f":null}]},
	{"c":[{"v":2003,"f":null},{"v":342.3,"f":null},{"v":46.3,"f":null},{"v":296.1,"f":null}]},
	{"c":[{"v":2004,"f":null},{"v":365,"f":null},{"v":49.2,"f":null},{"v":315.9,"f":null}]},
	{"c":[{"v":2005,"f":null},{"v":422.3,"f":null},{"v":58.7,"f":null},{"v":363.5,"f":null}]},
	{"c":[{"v":2006,"f":null},{"v":427.8,"f":null},{"v":58.8,"f":null},{"v":369,"f":null}]},
	{"c":[{"v":2007,"f":null},{"v":448.6,"f":null},{"v":61.5,"f":null},{"v":387.1,"f":null}]},
	{"c":[{"v":2008,"f":null},{"v":427.1,"f":null},{"v":58.4,"f":null},{"v":368.7,"f":null}]},
	{"c":[{"v":2009,"f":null},{"v":528.6,"f":null},{"v":55.3,"f":null},{"v":473.3,"f":null}]},
	{"c":[{"v":2010,"f":null},{"v":602.6,"f":null},{"v":63.5,"f":null},{"v":539,"f":null}]},
	{"c":[{"v":2011,"f":null},{"v":706.1,"f":null},{"v":73.8,"f":null},{"v":632.3,"f":null}]}
	]
}