[{"Tempo":1983,"Total":"7,6","Masculino":"4,6","Feminino":"11,6"},
{"Tempo":1984,"Total":"8,2","Masculino":"5,8","Feminino":"11,6"},
{"Tempo":1985,"Total":"8,5","Masculino":"6,3","Feminino":"11,6"},
{"Tempo":1986,"Total":"8,3","Masculino":"6,4","Feminino":"10,9"},
{"Tempo":1987,"Total":"6,8","Masculino":"5,2","Feminino":"9,1"},
{"Tempo":1988,"Total":"5,6","Masculino":"4","Feminino":"7,8"},
{"Tempo":1989,"Total":"5","Masculino":"3,4","Feminino":"7"},
{"Tempo":1990,"Total":"4,6","Masculino":"3,2","Feminino":"6,5"},
{"Tempo":1991,"Total":"4,1","Masculino":"2,7","Feminino":"5,8"},
{"Tempo":1992,"Total":"4,1","Masculino":"3,4","Feminino":"4,9"},
{"Tempo":1993,"Total":"5,5","Masculino":"4,6","Feminino":"6,5"},
{"Tempo":1994,"Total":"6,8","Masculino":"5,9","Feminino":"7,8"},
{"Tempo":1995,"Total":"7,1","Masculino":"6,3","Feminino":"8,1"},
{"Tempo":1996,"Total":"7,2","Masculino":"6,4","Feminino":"8,2"},
{"Tempo":1997,"Total":"6,7","Masculino":"6","Feminino":"7,5"},
{"Tempo":1998,"Total":"4,9","Masculino":"3,9","Feminino":"6,2"},
{"Tempo":1999,"Total":"4,4","Masculino":"3,9","Feminino":"5"},
{"Tempo":2000,"Total":"3,9","Masculino":"3,1","Feminino":"4,9"},
{"Tempo":2001,"Total":"4","Masculino":"3,2","Feminino":"5"},
{"Tempo":2002,"Total":"5","Masculino":"4,1","Feminino":"6"},
{"Tempo":2003,"Total":"6,3","Masculino":"5,5","Feminino":"7,2"},
{"Tempo":2004,"Total":"6,7","Masculino":"5,8","Feminino":"7,6"},
{"Tempo":2005,"Total":"7,6","Masculino":"6,7","Feminino":"8,7"},
{"Tempo":2006,"Total":"7,7","Masculino":"6,5","Feminino":"9"},
{"Tempo":2007,"Total":"8","Masculino":"6,6","Feminino":"9,6"},
{"Tempo":2008,"Total":"7,6","Masculino":"6,5","Feminino":"8,8"},
{"Tempo":2009,"Total":"9,5","Masculino":"8,9","Feminino":"10,2"},
{"Tempo":2010,"Total":"10,8","Masculino":"9,8","Feminino":"11,9"},
{"Tempo":2011,"Total":"12,7","Masculino":"12,4","Feminino":"13,1"}]